{
  "AAPL": {
    "symbol": "AAPL",
    "buyOrders": [
      {
        "id": "ORD_1775306809567_ozish48la",
        "type": "BUY",
        "orderType": "LIMIT",
        "price": 243.64,
        "quantity": 21,
        "originalQuantity": 39,
        "timestamp": 1775306809567,
        "username": "system",
        "symbol": "AAPL"
      },
      {
        "id": "ORD_1775307747543_jhrodavqp",
        "type": "BUY",
        "orderType": "LIMIT",
        "price": 239.11,
        "quantity": 23,
        "originalQuantity": 77,
        "timestamp": 1775307747543,
        "username": "system",
        "symbol": "AAPL"
      },
      {
        "id": "ORD_1775307992799_ir07bv3w7",
        "type": "BUY",
        "orderType": "LIMIT",
        "price": 235.04,
        "quantity": 23,
        "originalQuantity": 23,
        "timestamp": 1775307992799,
        "username": "system",
        "symbol": "AAPL"
      },
      {
        "id": "ORD_1775306529272_04fwjpvsi",
        "type": "BUY",
        "orderType": "LIMIT",
        "price": 234.8,
        "quantity": 43,
        "originalQuantity": 43,
        "timestamp": 1775306529272,
        "username": "system",
        "symbol": "AAPL"
      },
      {
        "id": "ORD_1775307720508_3znlx5qqq",
        "type": "BUY",
        "orderType": "LIMIT",
        "price": 234.01,
        "quantity": 4,
        "originalQuantity": 19,
        "timestamp": 1775307720508,
        "username": "system",
        "symbol": "AAPL"
      },
      {
        "id": "ORD_1775307743538_l0jdteoer",
        "type": "BUY",
        "orderType": "LIMIT",
        "price": 232.75,
        "quantity": 62,
        "originalQuantity": 92,
        "timestamp": 1775307743538,
        "username": "system",
        "symbol": "AAPL"
      },
      {
        "id": "ORD_1775307414200_hurhn24so",
        "type": "BUY",
        "orderType": "LIMIT",
        "price": 231.9,
        "quantity": 59,
        "originalQuantity": 91,
        "timestamp": 1775307414200,
        "username": "system",
        "symbol": "AAPL"
      },
      {
        "id": "ORD_1775307705492_jv6silzba",
        "type": "BUY",
        "orderType": "LIMIT",
        "price": 231.02,
        "quantity": 22,
        "originalQuantity": 59,
        "timestamp": 1775307705492,
        "username": "system",
        "symbol": "AAPL"
      },
      {
        "id": "ORD_1775307927730_jxhgm2cv6",
        "type": "BUY",
        "orderType": "LIMIT",
        "price": 228.27,
        "quantity": 45,
        "originalQuantity": 45,
        "timestamp": 1775307927730,
        "username": "system",
        "symbol": "AAPL"
      },
      {
        "id": "ORD_1775306357104_lgui76oi6",
        "type": "BUY",
        "orderType": "LIMIT",
        "price": 226.85,
        "quantity": 6,
        "originalQuantity": 49,
        "timestamp": 1775306357104,
        "username": "system",
        "symbol": "AAPL"
      },
      {
        "id": "ORD_1775307472255_kcl896zc8",
        "type": "BUY",
        "orderType": "LIMIT",
        "price": 226.13,
        "quantity": 11,
        "originalQuantity": 29,
        "timestamp": 1775307472255,
        "username": "system",
        "symbol": "AAPL"
      },
      {
        "id": "ORD_1775307919723_7dbq9qsh6",
        "type": "BUY",
        "orderType": "LIMIT",
        "price": 225.44,
        "quantity": 34,
        "originalQuantity": 98,
        "timestamp": 1775307919723,
        "username": "system",
        "symbol": "AAPL"
      },
      {
        "id": "ORD_1775307022788_ufbabmmjc",
        "type": "BUY",
        "orderType": "LIMIT",
        "price": 224.83,
        "quantity": 30,
        "originalQuantity": 30,
        "timestamp": 1775307022788,
        "username": "system",
        "symbol": "AAPL"
      },
      {
        "id": "ORD_1775306410157_iskj66qnj",
        "type": "BUY",
        "orderType": "LIMIT",
        "price": 224.81,
        "quantity": 1,
        "originalQuantity": 14,
        "timestamp": 1775306410157,
        "username": "system",
        "symbol": "AAPL"
      },
      {
        "id": "ORD_1775308471325_s9iist4tw",
        "type": "BUY",
        "orderType": "LIMIT",
        "price": 224.55,
        "quantity": 33,
        "originalQuantity": 34,
        "timestamp": 1775308471325,
        "username": "system",
        "symbol": "AAPL"
      },
      {
        "id": "ORD_1775307650436_d3f7h0tb4",
        "type": "BUY",
        "orderType": "LIMIT",
        "price": 224.5,
        "quantity": 26,
        "originalQuantity": 26,
        "timestamp": 1775307650436,
        "username": "system",
        "symbol": "AAPL"
      },
      {
        "id": "ORD_1775307926729_d4jwund76",
        "type": "BUY",
        "orderType": "LIMIT",
        "price": 224.45,
        "quantity": 32,
        "originalQuantity": 32,
        "timestamp": 1775307926729,
        "username": "system",
        "symbol": "AAPL"
      },
      {
        "id": "ORD_1775308198017_tgli9l04o",
        "type": "BUY",
        "orderType": "LIMIT",
        "price": 223.61,
        "quantity": 90,
        "originalQuantity": 90,
        "timestamp": 1775308198017,
        "username": "system",
        "symbol": "AAPL"
      },
      {
        "id": "ORD_1775308231051_uafkuq10m",
        "type": "BUY",
        "orderType": "LIMIT",
        "price": 222.39,
        "quantity": 63,
        "originalQuantity": 63,
        "timestamp": 1775308231051,
        "username": "system",
        "symbol": "AAPL"
      },
      {
        "id": "ORD_1775307736531_ypimwg835",
        "type": "BUY",
        "orderType": "LIMIT",
        "price": 221.82,
        "quantity": 91,
        "originalQuantity": 91,
        "timestamp": 1775307736531,
        "username": "system",
        "symbol": "AAPL"
      },
      {
        "id": "ORD_1775307778584_7kblt25iu",
        "type": "BUY",
        "orderType": "LIMIT",
        "price": 221.43,
        "quantity": 27,
        "originalQuantity": 52,
        "timestamp": 1775307778584,
        "username": "system",
        "symbol": "AAPL"
      },
      {
        "id": "ORD_1775308055873_sdgs0e06s",
        "type": "BUY",
        "orderType": "LIMIT",
        "price": 221.22,
        "quantity": 30,
        "originalQuantity": 30,
        "timestamp": 1775308055873,
        "username": "system",
        "symbol": "AAPL"
      },
      {
        "id": "ORD_1775308020839_3b7q9wx7r",
        "type": "BUY",
        "orderType": "LIMIT",
        "price": 220.78,
        "quantity": 94,
        "originalQuantity": 94,
        "timestamp": 1775308020839,
        "username": "system",
        "symbol": "AAPL"
      },
      {
        "id": "ORD_1775308071887_rmwizs5es",
        "type": "BUY",
        "orderType": "LIMIT",
        "price": 220.69,
        "quantity": 73,
        "originalQuantity": 73,
        "timestamp": 1775308071887,
        "username": "system",
        "symbol": "AAPL"
      },
      {
        "id": "ORD_1775308313141_ol1pmgrl1",
        "type": "BUY",
        "orderType": "LIMIT",
        "price": 219.99,
        "quantity": 100,
        "originalQuantity": 100,
        "timestamp": 1775308313141,
        "username": "system",
        "symbol": "AAPL"
      },
      {
        "id": "ORD_1775308044862_oxgfrqwun",
        "type": "BUY",
        "orderType": "LIMIT",
        "price": 219.81,
        "quantity": 54,
        "originalQuantity": 54,
        "timestamp": 1775308044862,
        "username": "system",
        "symbol": "AAPL"
      },
      {
        "id": "ORD_1775307185952_s6m6cafb2",
        "type": "BUY",
        "orderType": "LIMIT",
        "price": 219.07,
        "quantity": 3,
        "originalQuantity": 12,
        "timestamp": 1775307185952,
        "username": "system",
        "symbol": "AAPL"
      },
      {
        "id": "ORD_1775307706493_5o7fohmdo",
        "type": "BUY",
        "orderType": "LIMIT",
        "price": 218.96,
        "quantity": 79,
        "originalQuantity": 79,
        "timestamp": 1775307706493,
        "username": "system",
        "symbol": "AAPL"
      },
      {
        "id": "ORD_1775308100915_9ov9100a3",
        "type": "BUY",
        "orderType": "LIMIT",
        "price": 218.89,
        "quantity": 92,
        "originalQuantity": 92,
        "timestamp": 1775308100915,
        "username": "system",
        "symbol": "AAPL"
      },
      {
        "id": "ORD_1775305875599_zy8rpciga",
        "type": "BUY",
        "orderType": "LIMIT",
        "price": 217.91,
        "quantity": 87,
        "originalQuantity": 87,
        "timestamp": 1775305875600,
        "username": "system",
        "symbol": "AAPL"
      },
      {
        "id": "ORD_1775305953678_5csfnw3g4",
        "type": "BUY",
        "orderType": "LIMIT",
        "price": 217.85,
        "quantity": 17,
        "originalQuantity": 17,
        "timestamp": 1775305953678,
        "username": "system",
        "symbol": "AAPL"
      },
      {
        "id": "ORD_1775307836640_lff7lg3nj",
        "type": "BUY",
        "orderType": "LIMIT",
        "price": 217.63,
        "quantity": 77,
        "originalQuantity": 77,
        "timestamp": 1775307836640,
        "username": "system",
        "symbol": "AAPL"
      },
      {
        "id": "ORD_1775306701461_7ieedv3xf",
        "type": "BUY",
        "orderType": "LIMIT",
        "price": 217.5,
        "quantity": 28,
        "originalQuantity": 41,
        "timestamp": 1775306701461,
        "username": "system",
        "symbol": "AAPL"
      },
      {
        "id": "ORD_1775306123849_53kd7nlbn",
        "type": "BUY",
        "orderType": "LIMIT",
        "price": 217.44,
        "quantity": 23,
        "originalQuantity": 23,
        "timestamp": 1775306123849,
        "username": "system",
        "symbol": "AAPL"
      },
      {
        "id": "ORD_1775307058820_kd2zagrjz",
        "type": "BUY",
        "orderType": "LIMIT",
        "price": 217.01,
        "quantity": 99,
        "originalQuantity": 99,
        "timestamp": 1775307058820,
        "username": "system",
        "symbol": "AAPL"
      },
      {
        "id": "ORD_1775307234008_2tg6056fz",
        "type": "BUY",
        "orderType": "LIMIT",
        "price": 217.01,
        "quantity": 39,
        "originalQuantity": 39,
        "timestamp": 1775307234008,
        "username": "system",
        "symbol": "AAPL"
      },
      {
        "id": "ORD_1775307051813_5old413az",
        "type": "BUY",
        "orderType": "LIMIT",
        "price": 216.97,
        "quantity": 66,
        "originalQuantity": 66,
        "timestamp": 1775307051813,
        "username": "system",
        "symbol": "AAPL"
      },
      {
        "id": "ORD_1775308380224_lw66ss6z7",
        "type": "BUY",
        "orderType": "LIMIT",
        "price": 216.83,
        "quantity": 32,
        "originalQuantity": 57,
        "timestamp": 1775308380224,
        "username": "system",
        "symbol": "AAPL"
      },
      {
        "id": "ORD_1775304796473_7b4eob6ra",
        "type": "BUY",
        "orderType": "LIMIT",
        "price": 216.6,
        "quantity": 61,
        "originalQuantity": 61,
        "timestamp": 1775304796473,
        "username": "system",
        "symbol": "AAPL"
      },
      {
        "id": "ORD_1775308101916_9te76pwc3",
        "type": "BUY",
        "orderType": "LIMIT",
        "price": 216.44,
        "quantity": 94,
        "originalQuantity": 94,
        "timestamp": 1775308101916,
        "username": "system",
        "symbol": "AAPL"
      },
      {
        "id": "ORD_1775307780586_4n1unzua6",
        "type": "BUY",
        "orderType": "LIMIT",
        "price": 216.08,
        "quantity": 59,
        "originalQuantity": 59,
        "timestamp": 1775307780586,
        "username": "system",
        "symbol": "AAPL"
      },
      {
        "id": "ORD_1775306750507_5yvj7mnrg",
        "type": "BUY",
        "orderType": "LIMIT",
        "price": 216.07,
        "quantity": 26,
        "originalQuantity": 88,
        "timestamp": 1775306750507,
        "username": "system",
        "symbol": "AAPL"
      },
      {
        "id": "ORD_1775307455240_l553scpak",
        "type": "BUY",
        "orderType": "LIMIT",
        "price": 215.85,
        "quantity": 68,
        "originalQuantity": 68,
        "timestamp": 1775307455240,
        "username": "system",
        "symbol": "AAPL"
      },
      {
        "id": "ORD_1775304958645_jyxdwc0ps",
        "type": "BUY",
        "orderType": "LIMIT",
        "price": 215.76,
        "quantity": 99,
        "originalQuantity": 99,
        "timestamp": 1775304958645,
        "username": "system",
        "symbol": "AAPL"
      },
      {
        "id": "ORD_1775304296978_tlmr5oz21",
        "type": "BUY",
        "orderType": "LIMIT",
        "price": 215.65,
        "quantity": 37,
        "originalQuantity": 37,
        "timestamp": 1775304296978,
        "username": "system",
        "symbol": "AAPL"
      },
      {
        "id": "ORD_1775307571352_g85by0ccn",
        "type": "BUY",
        "orderType": "LIMIT",
        "price": 215.48,
        "quantity": 68,
        "originalQuantity": 68,
        "timestamp": 1775307571352,
        "username": "system",
        "symbol": "AAPL"
      },
      {
        "id": "ORD_1775307532315_evif3xz94",
        "type": "BUY",
        "orderType": "LIMIT",
        "price": 215.45,
        "quantity": 43,
        "originalQuantity": 50,
        "timestamp": 1775307532315,
        "username": "system",
        "symbol": "AAPL"
      },
      {
        "id": "ORD_1775305617321_p538jh6qd",
        "type": "BUY",
        "orderType": "LIMIT",
        "price": 215.31,
        "quantity": 47,
        "originalQuantity": 47,
        "timestamp": 1775305617321,
        "username": "system",
        "symbol": "AAPL"
      },
      {
        "id": "ORD_1775305843557_5l9de1i7l",
        "type": "BUY",
        "orderType": "LIMIT",
        "price": 215.29,
        "quantity": 32,
        "originalQuantity": 97,
        "timestamp": 1775305843557,
        "username": "system",
        "symbol": "AAPL"
      },
      {
        "id": "ORD_1775304386068_ml7phcuyu",
        "type": "BUY",
        "orderType": "LIMIT",
        "price": 215.25,
        "quantity": 32,
        "originalQuantity": 32,
        "timestamp": 1775304386068,
        "username": "system",
        "symbol": "AAPL"
      },
      {
        "id": "ORD_1775306721480_65bsuq0bs",
        "type": "BUY",
        "orderType": "LIMIT",
        "price": 214.87,
        "quantity": 83,
        "originalQuantity": 83,
        "timestamp": 1775306721480,
        "username": "system",
        "symbol": "AAPL"
      },
      {
        "id": "ORD_1775304448131_o0ocsb8l0",
        "type": "BUY",
        "orderType": "LIMIT",
        "price": 214.7,
        "quantity": 62,
        "originalQuantity": 62,
        "timestamp": 1775304448131,
        "username": "system",
        "symbol": "AAPL"
      },
      {
        "id": "ORD_1775307759566_xfifwiuge",
        "type": "BUY",
        "orderType": "LIMIT",
        "price": 214.6,
        "quantity": 27,
        "originalQuantity": 27,
        "timestamp": 1775307759566,
        "username": "system",
        "symbol": "AAPL"
      },
      {
        "id": "ORD_1775305021707_1e7k1wjjz",
        "type": "BUY",
        "orderType": "LIMIT",
        "price": 214.55,
        "quantity": 19,
        "originalQuantity": 19,
        "timestamp": 1775305021707,
        "username": "system",
        "symbol": "AAPL"
      },
      {
        "id": "ORD_1775304537218_udhq62jyy",
        "type": "BUY",
        "orderType": "LIMIT",
        "price": 214.54,
        "quantity": 42,
        "originalQuantity": 42,
        "timestamp": 1775304537218,
        "username": "system",
        "symbol": "AAPL"
      },
      {
        "id": "ORD_1775304025709_tn4arjgot",
        "type": "BUY",
        "orderType": "LIMIT",
        "price": 214.53,
        "quantity": 12,
        "originalQuantity": 12,
        "timestamp": 1775304025709,
        "username": "system",
        "symbol": "AAPL"
      },
      {
        "id": "ORD_1775308098913_uuvxabdj3",
        "type": "BUY",
        "orderType": "LIMIT",
        "price": 214.48,
        "quantity": 19,
        "originalQuantity": 19,
        "timestamp": 1775308098913,
        "username": "system",
        "symbol": "AAPL"
      },
      {
        "id": "ORD_1775305157847_z4lnmtqut",
        "type": "BUY",
        "orderType": "LIMIT",
        "price": 214.45,
        "quantity": 10,
        "originalQuantity": 10,
        "timestamp": 1775305157847,
        "username": "system",
        "symbol": "AAPL"
      },
      {
        "id": "ORD_1775307307081_yzt2mzyei",
        "type": "BUY",
        "orderType": "LIMIT",
        "price": 214.41,
        "quantity": 14,
        "originalQuantity": 14,
        "timestamp": 1775307307081,
        "username": "system",
        "symbol": "AAPL"
      },
      {
        "id": "ORD_1775305541246_orfjgp5mr",
        "type": "BUY",
        "orderType": "LIMIT",
        "price": 214.33,
        "quantity": 82,
        "originalQuantity": 82,
        "timestamp": 1775305541246,
        "username": "system",
        "symbol": "AAPL"
      },
      {
        "id": "ORD_1775305570276_8mqdma4ti",
        "type": "BUY",
        "orderType": "LIMIT",
        "price": 214.17,
        "quantity": 97,
        "originalQuantity": 97,
        "timestamp": 1775305570276,
        "username": "system",
        "symbol": "AAPL"
      },
      {
        "id": "ORD_1775306732490_gbnw19ux9",
        "type": "BUY",
        "orderType": "LIMIT",
        "price": 213.95,
        "quantity": 16,
        "originalQuantity": 16,
        "timestamp": 1775306732490,
        "username": "system",
        "symbol": "AAPL"
      },
      {
        "id": "ORD_1775306248986_ekpltnrmr",
        "type": "BUY",
        "orderType": "LIMIT",
        "price": 213.94,
        "quantity": 39,
        "originalQuantity": 39,
        "timestamp": 1775306248986,
        "username": "system",
        "symbol": "AAPL"
      },
      {
        "id": "ORD_1775305644346_ovcwdn6xc",
        "type": "BUY",
        "orderType": "LIMIT",
        "price": 213.83,
        "quantity": 43,
        "originalQuantity": 43,
        "timestamp": 1775305644346,
        "username": "system",
        "symbol": "AAPL"
      },
      {
        "id": "ORD_1775308138953_e0kjgggx4",
        "type": "BUY",
        "orderType": "LIMIT",
        "price": 213.79,
        "quantity": 82,
        "originalQuantity": 82,
        "timestamp": 1775308138953,
        "username": "system",
        "symbol": "AAPL"
      },
      {
        "id": "ORD_1775306082809_wzxmwaxji",
        "type": "BUY",
        "orderType": "LIMIT",
        "price": 213.75,
        "quantity": 20,
        "originalQuantity": 20,
        "timestamp": 1775306082809,
        "username": "system",
        "symbol": "AAPL"
      },
      {
        "id": "ORD_1775306309056_6e2jakvuq",
        "type": "BUY",
        "orderType": "LIMIT",
        "price": 213.71,
        "quantity": 49,
        "originalQuantity": 49,
        "timestamp": 1775306309056,
        "username": "system",
        "symbol": "AAPL"
      },
      {
        "id": "ORD_1775304318002_m7p6g2yp3",
        "type": "BUY",
        "orderType": "LIMIT",
        "price": 213.64,
        "quantity": 3,
        "originalQuantity": 54,
        "timestamp": 1775304318002,
        "username": "system",
        "symbol": "AAPL"
      },
      {
        "id": "ORD_1775308452305_vh8xoqo8m",
        "type": "BUY",
        "orderType": "LIMIT",
        "price": 210.26,
        "quantity": 71,
        "originalQuantity": 71,
        "timestamp": 1775308452305,
        "username": "system",
        "symbol": "AAPL"
      },
      {
        "id": "ORD_1775308448299_132ne2q00",
        "type": "BUY",
        "orderType": "LIMIT",
        "price": 208.81,
        "quantity": 65,
        "originalQuantity": 79,
        "timestamp": 1775308448299,
        "username": "system",
        "symbol": "AAPL"
      },
      {
        "id": "ORD_1775308462316_m576jx9c4",
        "type": "BUY",
        "orderType": "LIMIT",
        "price": 204.77,
        "quantity": 55,
        "originalQuantity": 55,
        "timestamp": 1775308462316,
        "username": "system",
        "symbol": "AAPL"
      }
    ],
    "sellOrders": [],
    "lastTradedPrice": 217.64
  },
  "TSLA": {
    "symbol": "TSLA",
    "buyOrders": [
      {
        "id": "ORD_1775308447297_a52wlofsf",
        "type": "BUY",
        "orderType": "LIMIT",
        "price": 214.44,
        "quantity": 38,
        "originalQuantity": 40,
        "timestamp": 1775308447297,
        "username": "system",
        "symbol": "TSLA"
      },
      {
        "id": "ORD_1775308459313_eppaeuvpb",
        "type": "BUY",
        "orderType": "LIMIT",
        "price": 212.69,
        "quantity": 12,
        "originalQuantity": 12,
        "timestamp": 1775308459313,
        "username": "system",
        "symbol": "TSLA"
      },
      {
        "id": "ORD_1775308456309_07rml0ock",
        "type": "BUY",
        "orderType": "LIMIT",
        "price": 211.23,
        "quantity": 62,
        "originalQuantity": 62,
        "timestamp": 1775308456309,
        "username": "system",
        "symbol": "TSLA"
      },
      {
        "id": "ORD_1775308435282_eww742om9",
        "type": "BUY",
        "orderType": "LIMIT",
        "price": 203.38,
        "quantity": 58,
        "originalQuantity": 58,
        "timestamp": 1775308435282,
        "username": "system",
        "symbol": "TSLA"
      }
    ],
    "sellOrders": [
      {
        "id": "ORD_1775308472326_rr93rcy0q",
        "type": "SELL",
        "orderType": "LIMIT",
        "price": 217.04,
        "quantity": 67,
        "originalQuantity": 67,
        "timestamp": 1775308472326,
        "username": "system",
        "symbol": "TSLA"
      }
    ],
    "lastTradedPrice": 207.1
  },
  "MSFT": {
    "symbol": "MSFT",
    "buyOrders": [
      {
        "id": "ORD_1775308470324_dswwvyjgy",
        "type": "BUY",
        "orderType": "LIMIT",
        "price": 484.62,
        "quantity": 21,
        "originalQuantity": 46,
        "timestamp": 1775308470324,
        "username": "system",
        "symbol": "MSFT"
      }
    ],
    "sellOrders": [],
    "lastTradedPrice": 462.4
  },
  "GOOGL": {
    "symbol": "GOOGL",
    "buyOrders": [
      {
        "id": "ORD_1775308355195_jnw70styw",
        "type": "BUY",
        "orderType": "LIMIT",
        "price": 235.25,
        "quantity": 46,
        "originalQuantity": 46,
        "timestamp": 1775308355195,
        "username": "system",
        "symbol": "GOOGL"
      },
      {
        "id": "ORD_1775308454307_jqnnegd9m",
        "type": "BUY",
        "orderType": "LIMIT",
        "price": 231.49,
        "quantity": 35,
        "originalQuantity": 46,
        "timestamp": 1775308454307,
        "username": "system",
        "symbol": "GOOGL"
      },
      {
        "id": "ORD_1775308438287_66ypocqvv",
        "type": "BUY",
        "orderType": "LIMIT",
        "price": 230.32,
        "quantity": 16,
        "originalQuantity": 16,
        "timestamp": 1775308438287,
        "username": "system",
        "symbol": "GOOGL"
      },
      {
        "id": "ORD_1775308364204_8e2x16dtu",
        "type": "BUY",
        "orderType": "LIMIT",
        "price": 224.22,
        "quantity": 39,
        "originalQuantity": 39,
        "timestamp": 1775308364204,
        "username": "system",
        "symbol": "GOOGL"
      },
      {
        "id": "ORD_1775308319148_3kron0hdq",
        "type": "BUY",
        "orderType": "LIMIT",
        "price": 222.45,
        "quantity": 83,
        "originalQuantity": 83,
        "timestamp": 1775308319148,
        "username": "system",
        "symbol": "GOOGL"
      },
      {
        "id": "ORD_1775308353192_1qzh69oeu",
        "type": "BUY",
        "orderType": "LIMIT",
        "price": 220.37,
        "quantity": 76,
        "originalQuantity": 76,
        "timestamp": 1775308353192,
        "username": "system",
        "symbol": "GOOGL"
      },
      {
        "id": "ORD_1775308312140_hjiyonump",
        "type": "BUY",
        "orderType": "LIMIT",
        "price": 216.16,
        "quantity": 15,
        "originalQuantity": 85,
        "timestamp": 1775308312140,
        "username": "system",
        "symbol": "GOOGL"
      }
    ],
    "sellOrders": [],
    "lastTradedPrice": 216.16
  },
  "NIFTY": {
    "symbol": "NIFTY",
    "buyOrders": [
      {
        "id": "ORD_1775308302128_2ro4dwzk9",
        "type": "BUY",
        "orderType": "LIMIT",
        "price": 26456.79,
        "quantity": 33,
        "originalQuantity": 56,
        "timestamp": 1775308302128,
        "username": "system",
        "symbol": "NIFTY"
      },
      {
        "id": "ORD_1775308304130_9j9fpg6se",
        "type": "BUY",
        "orderType": "LIMIT",
        "price": 25052.13,
        "quantity": 88,
        "originalQuantity": 88,
        "timestamp": 1775308304130,
        "username": "system",
        "symbol": "NIFTY"
      },
      {
        "id": "ORD_1775308317145_zt85pucol",
        "type": "BUY",
        "orderType": "LIMIT",
        "price": 24978.38,
        "quantity": 76,
        "originalQuantity": 76,
        "timestamp": 1775308317145,
        "username": "system",
        "symbol": "NIFTY"
      },
      {
        "id": "ORD_1775307842644_r88jsqhlv",
        "type": "BUY",
        "orderType": "LIMIT",
        "price": 24404.93,
        "quantity": 46,
        "originalQuantity": 46,
        "timestamp": 1775307842644,
        "username": "system",
        "symbol": "NIFTY"
      },
      {
        "id": "ORD_1775308038856_fuey1idsm",
        "type": "BUY",
        "orderType": "LIMIT",
        "price": 24071.36,
        "quantity": 41,
        "originalQuantity": 65,
        "timestamp": 1775308038856,
        "username": "system",
        "symbol": "NIFTY"
      },
      {
        "id": "ORD_1775307715503_pm4yjzjqr",
        "type": "BUY",
        "orderType": "LIMIT",
        "price": 23817.95,
        "quantity": 100,
        "originalQuantity": 100,
        "timestamp": 1775307715503,
        "username": "system",
        "symbol": "NIFTY"
      },
      {
        "id": "ORD_1775308199017_4s7wqrup3",
        "type": "BUY",
        "orderType": "LIMIT",
        "price": 23787.48,
        "quantity": 86,
        "originalQuantity": 86,
        "timestamp": 1775308199017,
        "username": "system",
        "symbol": "NIFTY"
      },
      {
        "id": "ORD_1775308223043_mya9ivfqt",
        "type": "BUY",
        "orderType": "LIMIT",
        "price": 23463.94,
        "quantity": 98,
        "originalQuantity": 98,
        "timestamp": 1775308223043,
        "username": "system",
        "symbol": "NIFTY"
      },
      {
        "id": "ORD_1775308339178_3uw38dpql",
        "type": "BUY",
        "orderType": "LIMIT",
        "price": 23431.08,
        "quantity": 4,
        "originalQuantity": 85,
        "timestamp": 1775308339178,
        "username": "system",
        "symbol": "NIFTY"
      },
      {
        "id": "ORD_1775308366207_1ywmcnb4o",
        "type": "BUY",
        "orderType": "LIMIT",
        "price": 23426.86,
        "quantity": 20,
        "originalQuantity": 80,
        "timestamp": 1775308366207,
        "username": "system",
        "symbol": "NIFTY"
      },
      {
        "id": "ORD_1775308464318_u33q6xwbo",
        "type": "BUY",
        "orderType": "LIMIT",
        "price": 22325.35,
        "quantity": 21,
        "originalQuantity": 21,
        "timestamp": 1775308464318,
        "username": "system",
        "symbol": "NIFTY"
      }
    ],
    "sellOrders": [
      {
        "id": "ORD_1775308467321_lilpoaphv",
        "type": "SELL",
        "orderType": "LIMIT",
        "price": 22470.29,
        "quantity": 54,
        "originalQuantity": 66,
        "timestamp": 1775308467321,
        "username": "system",
        "symbol": "NIFTY"
      },
      {
        "id": "ORD_1775308431279_z7i07frrz",
        "type": "SELL",
        "orderType": "LIMIT",
        "price": 23044.62,
        "quantity": 69,
        "originalQuantity": 80,
        "timestamp": 1775308431279,
        "username": "system",
        "symbol": "NIFTY"
      },
      {
        "id": "ORD_1775308465319_bpe8qqf2a",
        "type": "SELL",
        "orderType": "LIMIT",
        "price": 23560.16,
        "quantity": 32,
        "originalQuantity": 32,
        "timestamp": 1775308465319,
        "username": "system",
        "symbol": "NIFTY"
      },
      {
        "id": "ORD_1775308457310_vv80c1wkf",
        "type": "SELL",
        "orderType": "LIMIT",
        "price": 23944.22,
        "quantity": 41,
        "originalQuantity": 41,
        "timestamp": 1775308457310,
        "username": "system",
        "symbol": "NIFTY"
      },
      {
        "id": "ORD_1775308309136_o00f1w5no",
        "type": "SELL",
        "orderType": "LIMIT",
        "price": 26089.4,
        "quantity": 94,
        "originalQuantity": 94,
        "timestamp": 1775308309136,
        "username": "system",
        "symbol": "NIFTY"
      }
    ],
    "lastTradedPrice": 22470.29
  }
}